minio/__init__.py
minio/api.py
minio/compat.py
minio/definitions.py
minio/error.py
minio/helpers.py
minio/limited_reader.py
minio/parsers.py
minio/post_policy.py
minio/signer.py
minio/xml_marshal.py
minio_py3-1.0.1.1.dist-info/DESCRIPTION.rst
minio_py3-1.0.1.1.dist-info/METADATA
minio_py3-1.0.1.1.dist-info/RECORD
minio_py3-1.0.1.1.dist-info/WHEEL
minio_py3-1.0.1.1.dist-info/metadata.json
minio_py3-1.0.1.1.dist-info/top_level.txt
