Metadata-Version: 2.0
Name: minio-py3
Version: 1.0.1.1
Summary: Minio Python Library for Amazon S3 Compatible Cloud Storage for Python
Home-page: https://github.com/minio/minio-py
Author: Minio, Inc.
Author-email: dev@minio.io
License: Apache License 2.0
Download-URL: https://github.com/minio/minio-py
Platform: UNKNOWN
Classifier: Development Status :: 4 - Beta
Classifier: Intended Audience :: Developers
Classifier: Natural Language :: English
Classifier: License :: OSI Approved :: Apache Software License
Classifier: Operating System :: OS Independent
Classifier: Programming Language :: Python
Classifier: Programming Language :: Python :: 2.7
Classifier: Programming Language :: Python :: 3.3
Classifier: Programming Language :: Python :: 3.4
Classifier: Programming Language :: Python :: 3.5
Classifier: Topic :: Software Development :: Libraries :: Python Modules
Requires-Dist: certifi (<=2015.4.28)
Requires-Dist: pytz
Requires-Dist: urllib3
